sgd_boost/__init__.py
sgd_boost/__version__.py
sgd_boost/sgd_boost.py
sgd_boost-1.0.2.dist-info/LICENSE
sgd_boost-1.0.2.dist-info/METADATA
sgd_boost-1.0.2.dist-info/WHEEL
sgd_boost-1.0.2.dist-info/top_level.txt
sgd_boost-1.0.2.dist-info/RECORD
